voice2text.py
voice2text-0.1.1.dist-info/METADATA
voice2text-0.1.1.dist-info/WHEEL
voice2text-0.1.1.dist-info/entry_points.txt
voice2text-0.1.1.dist-info/licenses/LICENSE
voice2text-0.1.1.dist-info/RECORD
