Metadata-Version: 2.4
Name: voice2text
Version: 0.1.1
Summary: Local voice-to-text with Whisper + LLM cleanup
License-Expression: GPL-2.0-only
License-File: LICENSE
Requires-Python: >=3.11
Requires-Dist: loguru
Requires-Dist: mlx-whisper
Requires-Dist: numpy
Requires-Dist: pynput
Requires-Dist: scipy
Requires-Dist: sounddevice
